{
  "ETH-USDT": {
    "data": {
      "price": 1661.19,
      "change_24h": 6.05094,
      "market_cap": 200489208983,
      "volume_24h": 11597114081,
      "source": "CoinGecko"
    },
    "cached_at": 1744472794.181917
  },
  "ETH/USDT": {
    "data": {
      "price": 1661.19,
      "change_24h": 6.05094,
      "market_cap": 200489208983,
      "volume_24h": 11597114081,
      "source": "CoinGecko"
    },
    "cached_at": 1744472794.2460258
  },
  "BTC-USDT": {
    "data": {
      "price": 85205,
      "change_24h": 3.38229,
      "market_cap": 1689999770888,
      "volume_24h": 27489394321,
      "source": "CoinGecko"
    },
    "cached_at": 1744472794.0283108
  },
  "BTC/USDT": {
    "data": {
      "price": 85205,
      "change_24h": 3.38229,
      "market_cap": 1689999770888,
      "volume_24h": 27489394321,
      "source": "CoinGecko"
    },
    "cached_at": 1744472794.0915987
  },
  "XRP-USDT": {
    "data": {
      "price": 2.16,
      "change_24h": 8.05376,
      "market_cap": 126094865952,
      "volume_24h": 3010056638,
      "source": "CoinGecko"
    },
    "cached_at": 1744472794.3791993
  },
  "XRP/USDT": {
    "data": {
      "price": 2.16413123452738,
      "change_24h": 8.130960909039768,
      "market_cap": 216383373473.93317,
      "volume_24h": 319427350.797483,
      "source": "CryptoCompare"
    },
    "cached_at": 1744472794.8900545
  },
  "SOL-USDT": {
    "data": {
      "price": 130.963419503466,
      "change_24h": 9.208393704153195,
      "market_cap": 78352987794.0148,
      "volume_24h": 8777289.95654228,
      "source": "CryptoCompare"
    },
    "cached_at": 1744472796.0209281
  },
  "SOL/USDT": {
    "data": {
      "price": 130.925680508127,
      "change_24h": 9.176923732793181,
      "market_cap": 78330411504.01155,
      "volume_24h": 8777344.00944828,
      "source": "CryptoCompare"
    },
    "cached_at": 1744472797.5703156
  },
  "BITCOIN/USDT": {
    "data": {
      "price": 85106,
      "change_24h": 3.26239,
      "market_cap": 1689330205021,
      "volume_24h": 27366393658,
      "source": "CoinGecko"
    },
    "cached_at": 1744472332.248064
  },
  "ETHEREUM/USDT": {
    "data": {
      "price": 1660.2,
      "change_24h": 6.11893,
      "market_cap": 200360250236,
      "volume_24h": 11041429653,
      "source": "CoinGecko"
    },
    "cached_at": 1744472274.6703777
  },
  "SOLANA/USDT": {
    "data": {
      "price": 131.12,
      "change_24h": 9.88958,
      "market_cap": 67583223342,
      "volume_24h": 4345645667,
      "source": "CoinGecko"
    },
    "cached_at": 1744472275.3224201
  },
  "RIPPLE/USDT": {
    "data": {
      "price": 2.16,
      "change_24h": 7.80402,
      "market_cap": 126043845772,
      "volume_24h": 2984660023,
      "source": "CoinGecko"
    },
    "cached_at": 1744472277.332741
  },
  "BNB/USDT": {
    "data": {
      "price": 599.294495239822,
      "change_24h": 2.394208854919912,
      "market_cap": 85381882037.45946,
      "volume_24h": 181471.538501,
      "source": "CryptoCompare"
    },
    "cached_at": 1744471911.6943526
  }
}