{
  "ETH-USDT": {
    "data": {
      "price": 1653.81,
      "change_24h": 6.04395,
      "market_cap": 199593089307,
      "volume_24h": 11655124560,
      "source": "CoinGecko"
    },
    "cached_at": 1744474726.490842
  },
  "ETH/USDT": {
    "data": {
      "price": 1653.81,
      "change_24h": 6.04395,
      "market_cap": 199593089307,
      "volume_24h": 11655124560,
      "source": "CoinGecko"
    },
    "cached_at": 1744474726.5593143
  },
  "BTC-USDT": {
    "data": {
      "price": 84891,
      "change_24h": 3.13914,
      "market_cap": 1685660538570,
      "volume_24h": 27190811799,
      "source": "CoinGecko"
    },
    "cached_at": 1744474554.430274
  },
  "BTC/USDT": {
    "data": {
      "price": 84891,
      "change_24h": 3.13914,
      "market_cap": 1685660538570,
      "volume_24h": 27190811799,
      "source": "CoinGecko"
    },
    "cached_at": 1744474554.5098526
  },
  "XRP-USDT": {
    "data": {
      "price": 2.15202270876422,
      "change_24h": 7.042987086207426,
      "market_cap": 215172687351.6561,
      "volume_24h": 319000689.440479,
      "source": "CryptoCompare"
    },
    "cached_at": 1744474555.023551
  },
  "XRP/USDT": {
    "data": {
      "price": 2.15208347968603,
      "change_24h": 7.04600987075894,
      "market_cap": 215178763608.42862,
      "volume_24h": 318993459.087648,
      "source": "CryptoCompare"
    },
    "cached_at": 1744474555.5311265
  },
  "SOL-USDT": {
    "data": {
      "price": 130.193654860753,
      "change_24h": 8.518097514554256,
      "market_cap": 77892449671.7506,
      "volume_24h": 8679925.02546723,
      "source": "CryptoCompare"
    },
    "cached_at": 1744474556.0227277
  },
  "SOL/USDT": {
    "data": {
      "price": 130.131247426833,
      "change_24h": 8.466080110119236,
      "market_cap": 77855112461.18562,
      "volume_24h": 8681311.54074023,
      "source": "CryptoCompare"
    },
    "cached_at": 1744474556.5159457
  },
  "BITCOIN/USDT": {
    "data": {
      "price": 84893,
      "change_24h": 3.19693,
      "market_cap": 1685660538570,
      "volume_24h": 27152471032,
      "source": "CoinGecko"
    },
    "cached_at": 1744474616.5424924
  },
  "ETHEREUM/USDT": {
    "data": {
      "price": 1654.16,
      "change_24h": 6.06616,
      "market_cap": 199852689441,
      "volume_24h": 11661051455,
      "source": "CoinGecko"
    },
    "cached_at": 1744474617.2180603
  },
  "SOLANA/USDT": {
    "data": {
      "price": 130.41,
      "change_24h": 9.45015,
      "market_cap": 67301659442,
      "volume_24h": 4396006013,
      "source": "CoinGecko"
    },
    "cached_at": 1744474618.4747007
  },
  "RIPPLE/USDT": {
    "data": {
      "price": 2.15,
      "change_24h": 7.86387,
      "market_cap": 125606988394,
      "volume_24h": 3036192493,
      "source": "CoinGecko"
    },
    "cached_at": 1744474728.0055425
  },
  "BNB/USDT": {
    "data": {
      "price": 599.294495239822,
      "change_24h": 2.394208854919912,
      "market_cap": 85381882037.45946,
      "volume_24h": 181471.538501,
      "source": "CryptoCompare"
    },
    "cached_at": 1744471911.6943526
  }
}